fastq_downloader/__init__.py
fastq_downloader/__main__.py
fastq_downloader/helper/__init__.py
fastq_downloader/helper/accession_to_links.py
fastq_downloader/helper/construct_gsm_dict.py
fastq_downloader/helper/download_and_verify.py
fastq_downloader/helper/merge_files.py
fastq_downloader/helper/rename_files_by_run.py
fastq_downloader/snakemake/Snakefile
fastq_downloader/snakemake/__init__.py
fastq_downloader/tests/test_ebi_api.py
fastq_downloader-0.4.4.dist-info/entry_points.txt
fastq_downloader-0.4.4.dist-info/LICENSE
fastq_downloader-0.4.4.dist-info/WHEEL
fastq_downloader-0.4.4.dist-info/METADATA
fastq_downloader-0.4.4.dist-info/RECORD
