Metadata-Version: 2.1
Name: fastq-downloader
Version: 0.4.4
Summary: 
License: MIT
Author: tpob
Author-email: tpob@tpob.xyz
Requires-Python: >=3.8,<4.0
Classifier: License :: OSI Approved :: MIT License
Classifier: Programming Language :: Python :: 3
Classifier: Programming Language :: Python :: 3.10
Classifier: Programming Language :: Python :: 3.8
Classifier: Programming Language :: Python :: 3.9
Requires-Dist: beautifulsoup4
Requires-Dist: click
Requires-Dist: httpx
Requires-Dist: lxml
Requires-Dist: snakemake (>=6.10.0,<7.0.0)
